scdn/__init__.py
scdn/data_preprocess.py
scdn/evaluation.py
scdn/main_computation.py
scdn/model_config.py
scdn/scdn_analysis.py
scdn/validation_truncation_1.py
scdn-0.0.2.dist-info/METADATA
scdn-0.0.2.dist-info/RECORD
scdn-0.0.2.dist-info/WHEEL
scdn-0.0.2.dist-info/top_level.txt
